cc_adapter/__init__.py
cc_adapter/codex_auth.py
cc_adapter/codex_bridge.py
cc_adapter/codex_instructions.py
cc_adapter/codex_oauth.py
cc_adapter/codex_tool_remap.py
cc_adapter/config.py
cc_adapter/context_limits.py
cc_adapter/converters.py
cc_adapter/gui.py
cc_adapter/icon.png
cc_adapter/logging_utils.py
cc_adapter/model_registry.py
cc_adapter/models.py
cc_adapter/server.py
cc_adapter/streaming.py
cc_adapter/providers/__init__.py
cc_adapter/providers/codex.py
cc_adapter/providers/lmstudio.py
cc_adapter/providers/openrouter.py
cc_adapter/providers/poe.py
cc_adapter-0.25.1.dist-info/licenses/LICENSE
tests/test_codex_bridge_remap.py
tests/test_codex_bridge_system_strip.py
tests/test_codex_models.py
tests/test_codex_oauth.py
tests/test_codex_transform.py
tests/test_context_defaults.py
tests/test_converters.py
tests/test_model_spec_normalization.py
tests/test_poe_context.py
tests/test_poe_payload.py
tests/test_poe_retries.py
tests/test_provider_connectivity.py
tests/test_server_helpers.py
tests/test_streaming_errors.py
tests/test_streaming_responses.py
cc_adapter-0.25.1.dist-info/METADATA
cc_adapter-0.25.1.dist-info/WHEEL
cc_adapter-0.25.1.dist-info/entry_points.txt
cc_adapter-0.25.1.dist-info/top_level.txt
cc_adapter-0.25.1.dist-info/RECORD
