Metadata-Version: 2.4
Name: cc-adapter
Version: 0.25.1
Summary: Claude Code adapter for LM Studio / Poe / OpenRouter / OpenAI Codex (Subscription required)
Requires-Python: >=3.10
License-File: LICENSE
Requires-Dist: requests>=2.32.0
Requires-Dist: platformdirs>=4.3.6
Requires-Dist: tiktoken>=0.12.0
Provides-Extra: dev
Dynamic: license-file
